Workbook

Sheet Sheet1
A1: Date Engaged | B1: Employee Code | C1: First Name | D1: Last Name | E1: DEPARTMENT - Department | F1: Job Title | G1: Racial Group | H1: Gender | I1: OL - Operating Level | J1: Email Address | K1: Cell Number
A2: 38139 | B2: 10005 | C2: Michael | D2: Shapiro | E2: EXECUTIVE - Executive | F2: MD - Managing Director | G2: W - White | H2: M - Male | I2: DIR - Director | J2: =_xlfn.XLOOKUP(B2,Sheet!A4,Sheet!B4,0,) -> michael@synthesis.co.za | K2: =_xlfn.XLOOKUP(B2,Sheet!A:A,Sheet!C:C,FALSE,) -> 0833274929
A3: 38494 | B3: 10006 | C3: Naseem | D3: Ahmed | E3: CLD - Cloud | F3: CPEL - Cloud PL | G3: I - Indian | H3: M - Male | I3: PRINCIPAL - Principal | J3: =_xlfn.XLOOKUP(B3,Sheet!A5,Sheet!B5,0,) -> naseem@synthesis.co.za | K3: =_xlfn.XLOOKUP(B3,Sheet!A:A,Sheet!C:C,FALSE,) -> 0827493272
A4: 38139 | B4: 10009 | C4: Steyn | D4: Basson | E4: EXECUTIVE - Executive | F4: SSECD - Shared Services Executive & Company | G4: W - White | H4: M - Male | I4: DIR - Director | J4: =_xlfn.XLOOKUP(B4,Sheet!A6,Sheet!B6,0,) -> steyn@synthesis.co.za | K4: =_xlfn.XLOOKUP(B4,Sheet!A:A,Sheet!C:C,FALSE,) -> 0834501034
A5: 43252 | B5: AA01 | C5: Archana | D5: Arakkal | E5: TEC - Technology | F5: LRE - Lead Research Engineer | G5: I - Indian | H5: F - Female | I5: SPECIALIST - Specialist | J5: =_xlfn.XLOOKUP(B5,Sheet!A:A,Sheet!B:B,FALSE,) -> archana@synthesis.co.za | K5: =_xlfn.XLOOKUP(B5,Sheet!A:A,Sheet!C:C,FALSE,) -> 0834186862
A6: 44866 | B6: AC02 | C6: Angela | D6: Church | E6: 001 - Business Enablement Operations | F6: OM - Office Manager | G6: W - White | H6: F - Female | I6: INTERMEDIATE - Intermediate | J6: =_xlfn.XLOOKUP(B6,Sheet!A:A,Sheet!B:B,FALSE,) -> angie@synthesis.co.za | K6: =_xlfn.XLOOKUP(B6,Sheet!A:A,Sheet!C:C,FALSE,) -> 0636844757
A7: 44816 | B7: AH01 | C7: Arielle | D7: Horwitz | E7: HAL - Halo | F7: EM - Engineering Manager | G7: W - White | H7: F - Female | I7: INTERMEDIATE - Intermediate | J7: =_xlfn.XLOOKUP(B7,Sheet!A:A,Sheet!B:B,FALSE,) -> arielle@synthesis.co.za | K7: =_xlfn.XLOOKUP(B7,Sheet!A:A,Sheet!C:C,FALSE,) -> 0933955001
A8: 44562 | B8: AL03 | C8: Athini | D8: Ludidi | E8: MAN - Managed Operations | F8: SE03 - Senior Support Engineer | G8: A - African | H8: M - Male | I8: SENIOR - Senior | J8: =_xlfn.XLOOKUP(B8,Sheet!A:A,Sheet!B:B,FALSE,) -> athini@synthesis.co.za | K8: =_xlfn.XLOOKUP(B8,Sheet!A:A,Sheet!C:C,FALSE,) -> 0793866448
A9: 43437 | B9: AS02 | C9: Arno | D9: Strydom | E9: REGT - RegTech | F9: FINTL - Finsurv Team Lead | G9: W - White | H9: M - Male | I9: SENIOR - Senior | J9: =_xlfn.XLOOKUP(B9,Sheet!A:A,Sheet!B:B,FALSE,) -> arno@synthesis.co.za | K9: =_xlfn.XLOOKUP(B9,Sheet!A:A,Sheet!C:C,FALSE,) -> 0649063446
A10: 43466 | B10: BS02 | C10: Bhavesh | D10: Sooka | E10: ID - Intelligent Data | F10: SD - Software Dev | G10: I - Indian | H10: M - Male | I10: SENIOR - Senior | J10: =_xlfn.XLOOKUP(B10,Sheet!A:A,Sheet!B:B,FALSE,) -> bhavesh@synthesis.co.za | K10: =_xlfn.XLOOKUP(B10,Sheet!A:A,Sheet!C:C,FALSE,) -> 0825423485
A11: 44197 | B11: CD01 | C11: Claire | D11: Dann | E11: 001 - Business Enablement Operations | F11: LFOM - Lead Facilities and Office Manag | G11: W - White | H11: F - Female | I11: SENIOR - Senior | J11: =_xlfn.XLOOKUP(B11,Sheet!A:A,Sheet!B:B,FALSE,) -> claire@synthesis.co.za | K11: =_xlfn.XLOOKUP(B11,Sheet!A:A,Sheet!C:C,FALSE,) -> 0829658798
A12: 40544 | B12: CE01 | C12: Chad | D12: Epstein | E12: CLD - Cloud | F12: CPML - Cloud PL Migrat | G12: W - White | H12: M - Male | I12: PRINCIPAL - Principal | J12: =_xlfn.XLOOKUP(B12,Sheet!A:A,Sheet!B:B,FALSE,) -> chad@synthesis.co.za | K12: =_xlfn.XLOOKUP(B12,Sheet!A:A,Sheet!C:C,FALSE,) -> 0726304180
A13: 44788 | B13: CF01 | C13: Craig | D13: Fuchs | E13: COD - Code | F13: SP - Solutionist Principal | G13: W - White | H13: M - Male | I13: PRINCIPAL - Principal | J13: =_xlfn.XLOOKUP(B13,Sheet!A:A,Sheet!B:B,FALSE,) -> craigf@synthesis.co.za | K13: =_xlfn.XLOOKUP(B13,Sheet!A:A,Sheet!C:C,FALSE,) -> 0845861610
A14: 44896 | B14: CG01 | C14: Carly | D14: Garmany | E14: PMO - Project Management Office | F14: PMOO - PMO Operations Officer | G14: W - White | H14: F - Female | I14: INTERMEDIATE - Intermediate | J14: =_xlfn.XLOOKUP(B14,Sheet!A:A,Sheet!B:B,FALSE,) -> carly@synthesis.co.za | K14: =_xlfn.XLOOKUP(B14,Sheet!A:A,Sheet!C:C,FALSE,) -> 0797855692
A15: 44805 | B15: CM01 | C15: Cleorese | D15: Manes | E15: CLD - Cloud | F15: CE - Cloud Engineer | G15: C - Coloured | H15: F - Female | I15: INTERMEDIATE - Intermediate | J15: =_xlfn.XLOOKUP(B15,Sheet!A:A,Sheet!B:B,FALSE,) -> cleorese@synthesis.co.za | K15: =_xlfn.XLOOKUP(B15,Sheet!A:A,Sheet!C:C,FALSE,) -> 0607978655
A16: 42493 | B16: DB02 | C16: Darren | D16: Bak | E16: ID - Intelligent Data | F16: HOBD - Head of Intelligent Data | G16: W - White | H16: M - Male | I16: BU_HEAD - Business Unit Head | J16: =_xlfn.XLOOKUP(B16,Sheet!A:A,Sheet!B:B,FALSE,) -> darren@synthesis.co.za | K16: =_xlfn.XLOOKUP(B16,Sheet!A:A,Sheet!C:C,FALSE,) -> 0827833713
... A48: 43836 | B48: LM02 | C48: Lesego | D48: Mabe | E48: HAL - Halo | F48: SSE - Senior Software Engineer | G48: A - African | H48: M - Male | I48: SENIOR - Senior | J48: =_xlfn.XLOOKUP(B48,Sheet!A:A,Sheet!B:B,FALSE,) -> lesego@synthesis.co.za | K48: =_xlfn.XLOOKUP(B48,Sheet!A:A,Sheet!C:C,FALSE,) -> 0691047806
A49: 43891 | B49: LM03 | C49: Ntombifuthi | D49: Mkhosi | E49: 001 - Business Enablement Operations | F49: OC - Office Support | G49: A - African | H49: F - Female | I49: SS - Semi-skilled defined decision | K49: =_xlfn.XLOOKUP(B49,Sheet!A:A,Sheet!C:C,FALSE,) -> 0721791596
A50: 41807 | B50: LR02 | C50: Leandre | D50: Roux | E50: CLD - Cloud | F50: WARL - WAR Lead | G50: W - White | H50: M - Male | I50: SPECIALIST - Specialist | J50: =_xlfn.XLOOKUP(B50,Sheet!A:A,Sheet!B:B,FALSE,) -> leandre@synthesis.co.za | K50: =_xlfn.XLOOKUP(B50,Sheet!A:A,Sheet!C:C,FALSE,) -> 0723214345
A51: 43132 | B51: LS20 | C51: Louis-Philip | D51: Shahim | E51: CLD - Cloud | F51: GCPL - Google Cloud Practice Lead | G51: W - White | H51: M - Male | I51: PRINCIPAL - Principal | J51: =_xlfn.XLOOKUP(B51,Sheet!A:A,Sheet!B:B,FALSE,) -> louis-philip@synthesis.co.za | K51: =_xlfn.XLOOKUP(B51,Sheet!A:A,Sheet!C:C,FALSE,) -> 0729985673
A52: 42736 | B52: MB01 | C52: Marinda | D52: Rossouw | E52: REGT - RegTech | F52: PE03 - Senior Product Engineer | G52: W - White | H52: F - Female | I52: SENIOR - Senior | J52: =_xlfn.XLOOKUP(B52,Sheet!A:A,Sheet!B:B,FALSE,) -> marinda@synthesis.co.za | K52: =_xlfn.XLOOKUP(B52,Sheet!A:A,Sheet!C:C,FALSE,) -> 0783449276
A53: 41316 | B53: MC03 | C53: Matthew | D53: Crockett | E53: COD - Code | F53: HDG - Head: Digital | G53: W - White | H53: M - Male | I53: BU_HEAD - Business Unit Head | J53: =_xlfn.XLOOKUP(B53,Sheet!A:A,Sheet!B:B,FALSE,) -> matthew@synthesis.co.za | K53: =_xlfn.XLOOKUP(B53,Sheet!A:A,Sheet!C:C,FALSE,) -> 0833889105
A54: 43374 | B54: ME02 | C54: Michelle | D54: Esbend | E54: 002 - Finance | F54: FECD - Finance Executive & Company Directo | G54: C - Coloured | H54: F - Female | I54: DIR - Director | J54: =_xlfn.XLOOKUP(B54,Sheet!A:A,Sheet!B:B,FALSE,) -> michelle@synthesis.co.za | K54: =_xlfn.XLOOKUP(B54,Sheet!A:A,Sheet!C:C,FALSE,) -> 0713515463
A55: 44805 | B55: MG04 | C55: Michael | D55: Grant | E55: EXECUTIVE - Executive | F55: PDE - Product Development Executive | G55: W - White | H55: M - Male | I55: SM - Senior Manager | J55: =_xlfn.XLOOKUP(B55,Sheet!A:A,Sheet!B:B,FALSE,) -> MikeG@synthesis.co.za | K55: =_xlfn.XLOOKUP(B55,Sheet!A:A,Sheet!C:C,FALSE,) -> 0605597427
A56: 43731 | B56: MK02 | C56: Manthan | D56: Kuwadia | E56: 002 - Finance | F56: ACA - Accounts Assist | G56: I - Indian | H56: M - Male | I56: ASSOCIATE - Associate | J56: =_xlfn.XLOOKUP(B56,Sheet!A:A,Sheet!B:B,FALSE,) -> manthan@synthesis.co.za | K56: =_xlfn.XLOOKUP(B56,Sheet!A:A,Sheet!C:C,FALSE,) -> 0616491015
A57: 44606 | B57: MK03 | C57: Melissa | D57: Kramer | E57: HAL - Halo | F57: PMM - Product Marketing Manager | G57: W - White | H57: F - Female | I57: INTERMEDIATE - Intermediate | J57: =_xlfn.XLOOKUP(B57,Sheet!A:A,Sheet!B:B,FALSE,) -> melissak@synthesis.co.za | K57: =_xlfn.XLOOKUP(B57,Sheet!A:A,Sheet!C:C,FALSE,) -> 0614407113
A58: 42863 | B58: ML01 | C58: Miguel | D58: Laranjeira | E58: COD - Code | F58: T07 - Technical Lead | G58: W - White | H58: M - Male | I58: TECH - Tech Lead | J58: =_xlfn.XLOOKUP(B58,Sheet!A:A,Sheet!B:B,FALSE,) -> miguel@synthesis.co.za | K58: =_xlfn.XLOOKUP(B58,Sheet!A:A,Sheet!C:C,FALSE,) -> 0722179955
A59: 43832 | B59: MM01 | C59: Mark | D59: McNaughton | E59: MAN - Managed Operations | F59: SDOE - Snr DevOps Engineer | G59: W - White | H59: M - Male | I59: SENIOR - Senior | J59: =_xlfn.XLOOKUP(B59,Sheet!A:A,Sheet!B:B,FALSE,) -> mark@synthesis.co.za | K59: =_xlfn.XLOOKUP(B59,Sheet!A:A,Sheet!C:C,FALSE,) -> 0833258246
A60: 40422 | B60: MN01 | C60: Charles | D60: Neethling | E60: PI - Product Incubation | F60: HPI - Head: Product Incubation | G60: W - White | H60: M - Male | I60: BU_HEAD - Business Unit Head | J60: =_xlfn.XLOOKUP(B60,Sheet!A:A,Sheet!B:B,FALSE,) -> marais@synthesis.co.za | K60: =_xlfn.XLOOKUP(B60,Sheet!A:A,Sheet!C:C,FALSE,) -> 0825687420
A61: 44440 | B61: MN02 | C61: Mantombi | D61: Ngwenya | E61: 002 - Finance | F61: FM - Financial Manager | G61: A - African | H61: F - Female | I61: SENIOR - Senior | J61: =_xlfn.XLOOKUP(B61,Sheet!A:A,Sheet!B:B,FALSE,) -> mantombi@synthesis.co.za | K61: =_xlfn.XLOOKUP(B61,Sheet!A:A,Sheet!C:C,FALSE,) -> 0739501311
A62: 44748 | B62: MP07 | C62: Michael | D62: Phoya | E62: REGT - RegTech | F62: SE02 - Intermediate Support Engineer | G62: A - African | H62: M - Male | I62: INTERMEDIATE - Intermediate | J62: =_xlfn.XLOOKUP(B62,Sheet!A:A,Sheet!B:B,FALSE,) -> michael.p@synthesis.co.za | K62: =_xlfn.XLOOKUP(B62,Sheet!A:A,Sheet!C:C,FALSE,) -> 0781483503
A63: 41699 | B63: MS003 | C63: Mavis | D63: Sibisi | E63: 001 - Business Enablement Operations | F63: OC - Office Support | G63: A - African | H63: F - Female | I63: SS - Semi-skilled defined decision | K63: =_xlfn.XLOOKUP(B63,Sheet!A:A,Sheet!C:C,FALSE,) -> 0731672572
A64: 43132 | B64: MS04 | C64: Martin | D64: Streicher | E64: CLD - Cloud | F64: SSD - Snr SoftwareDev | G64: W - White | H64: M - Male | I64: SPECIALIST - Specialist | J64: =_xlfn.XLOOKUP(B64,Sheet!A:A,Sheet!B:B,FALSE,) -> martins@synthesis.co.za | K64: =_xlfn.XLOOKUP(B64,Sheet!A:A,Sheet!C:C,FALSE,) -> 0833823437
A65: 44197 | B65: MS06 | C65: Muhiya | D65: Sumba | E65: HAL - Halo | F65: ISE - Intermediate Software Engineer | G65: A - African | H65: M - Male | I65: INTERMEDIATE - Intermediate | J65: =_xlfn.XLOOKUP(B65,Sheet!A:A,Sheet!B:B,FALSE,) -> muhiya@synthesis.co.za | K65: =_xlfn.XLOOKUP(B65,Sheet!A:A,Sheet!C:C,FALSE,) -> 0738742017
A66: 44562 | B66: MV01 | C66: Mohammed | D66: Vally | E66: HAL - Halo | F66: ISE - Intermediate Software Engineer | G66: I - Indian | H66: M - Male | I66: INTERMEDIATE - Intermediate | J66: =_xlfn.XLOOKUP(B66,Sheet!A:A,Sheet!B:B,FALSE,) -> mohammedv@synthesis.co.za | K66: =_xlfn.XLOOKUP(B66,Sheet!A:A,Sheet!C:C,FALSE,) -> 0762907264
A67: 43709 | B67: MW001 | C67: Marcin | D67: Wójcik | E67: COD - Code | F67: SSE - Senior Software Engineer | G67: W - White | H67: M - Male | I67: SENIOR - Senior | J67: =_xlfn.XLOOKUP(B67,Sheet!A:A,Sheet!B:B,FALSE,) -> marcin@synthesis.co.za | K67: =_xlfn.XLOOKUP(B67,Sheet!A:A,Sheet!C:C,FALSE,) -> 0721378228
A68: 44835 | B68: ND01 | C68: Nicholas | D68: Driver | E68: CLD - Cloud | F68: SE - Software Engineer | G68: W - White | H68: M - Male | I68: SENIOR - Senior | J68: =_xlfn.XLOOKUP(B68,Sheet!A:A,Sheet!B:B,FALSE,) -> nicholasd@synthesis.co.za | K68: =_xlfn.XLOOKUP(B68,Sheet!A:A,Sheet!C:C,FALSE,) -> 0823955693
A69: 43739 | B69: NW003 | C69: Nigel | D69: Walker | E69: ID - Intelligent Data | F69: PME - Principal ML Engineer | G69: W - White | H69: M - Male | I69: SPECIALIST - Specialist | J69: =_xlfn.XLOOKUP(B69,Sheet!A:A,Sheet!B:B,FALSE,) -> nick@synthesis.co.za | K69: =_xlfn.XLOOKUP(B69,Sheet!A:A,Sheet!C:C,FALSE,) -> 0824686354
A70: 41456 | B70: PN01 | C70: Preshalin | D70: Naidoo | E70: COD - Code | F70: T07 - Technical Lead | G70: I - Indian | H70: M - Male | I70: TECH - Tech Lead | J70: =_xlfn.XLOOKUP(B70,Sheet!A:A,Sheet!B:B,FALSE,) -> preshalin@synthesis.co.za | K70: =_xlfn.XLOOKUP(B70,Sheet!A:A,Sheet!C:C,FALSE,) -> 0837669860
A71: 44743 | B71: QV01 | C71: Perfect | D71: Vumisa | E71: MAN - Managed Operations | F71: SOE02 - Intermediate SecOps Engineer | G71: A - African | H71: M - Male | I71: INTERMEDIATE - Intermediate | J71: =_xlfn.XLOOKUP(B71,Sheet!A:A,Sheet!B:B,FALSE,) -> qiniso@synthesis.co.za | K71: =_xlfn.XLOOKUP(B71,Sheet!A:A,Sheet!C:C,FALSE,) -> 0761905514
A72: 42614 | B72: RD01 | C72: Ricardo | D72: De Carvalho | E72: COD - Code | F72: SSE - Senior Software Engineer | G72: W - White | H72: M - Male | I72: SENIOR - Senior | J72: =_xlfn.XLOOKUP(B72,Sheet!A:A,Sheet!B:B,FALSE,) -> ricardo@synthesis.co.za | K72: =_xlfn.XLOOKUP(B72,Sheet!A:A,Sheet!C:C,FALSE,) -> 0836751898
A73: 43739 | B73: RD05 | C73: Rolf | D73: Deppe | E73: PAYMENTS - Payments | F73: SSE - Senior Software Engineer | G73: W - White | H73: M - Male | I73: SPECIALIST - Specialist | J73: =_xlfn.XLOOKUP(B73,Sheet!A:A,Sheet!B:B,FALSE,) -> rolf@synthesis.co.za | K73: =_xlfn.XLOOKUP(B73,Sheet!A:A,Sheet!C:C,FALSE,) -> 0840272395
A74: 44562 | B74: RD06 | C74: Ruben | D74: De Beer | E74: COD - Code | F74: ISE - Intermediate Software Engineer | G74: W - White | H74: M - Male | I74: INTERMEDIATE - Intermediate | J74: =_xlfn.XLOOKUP(B74,Sheet!A:A,Sheet!B:B,FALSE,) -> ruben@synthesis.co.za | K74: =_xlfn.XLOOKUP(B74,Sheet!A:A,Sheet!C:C,FALSE,) -> 0744697800
A75: 43344 | B75: RF01 | C75: Rui | D75: Felix | E75: CLD - Cloud | F75: SSD - Snr SoftwareDev | G75: W - White | H75: M - Male | I75: PRINCIPAL - Principal | J75: =_xlfn.XLOOKUP(B75,Sheet!A:A,Sheet!B:B,FALSE,) -> rui@synthesis.co.za | K75: =_xlfn.XLOOKUP(B75,Sheet!A:A,Sheet!C:C,FALSE,) -> 0795188596
... A111: 45153 | B111: SST000478 | C111: Nikita | D111: Venter | E111: 003 - Sales | F111: SAM - Strategic Account Manager | G111: W - White | H111: F - Female | I111: INTERMEDIATE - Intermediate | J111: =_xlfn.XLOOKUP(B111,Sheet!A:A,Sheet!B:B,FALSE,) -> nikita@synthesis.co.za | K111: =_xlfn.XLOOKUP(B111,Sheet!A:A,Sheet!C:C,FALSE,) -> 0605204725
A112: 45139 | B112: SST000479 | C112: Bathobile | D112: Sosibo | E112: 001 - Business Enablement Operations | F112: OC - Office Support | G112: A - African | H112: F - Female | I112: SS - Semi-skilled defined decision | K112: =_xlfn.XLOOKUP(B112,Sheet!A:A,Sheet!C:C,FALSE,) -> 0765181416
A113: 45170 | B113: SST000480 | C113: Nompumelelo | D113: Ndindane | E113: 001 - Business Enablement Operations | F113: OC - Office Support | G113: A - African | H113: F - Female | I113: SS - Semi-skilled defined decision | K113: =_xlfn.XLOOKUP(B113,Sheet!A:A,Sheet!C:C,FALSE,) -> 0660347965
A114: 45231 | B114: SST000483 | C114: Marcus | D114: Loveland | E114: REGT - RegTech | F114: PL - Product Lead | G114: W - White | H114: M - Male | I114: SPECIALIST - Specialist | J114: =_xlfn.XLOOKUP(B114,Sheet!A:A,Sheet!B:B,FALSE,) -> marcus@synthesis.co.za | K114: =_xlfn.XLOOKUP(B114,Sheet!A:A,Sheet!C:C,FALSE,) -> 0835675968
A115: 45231 | B115: SST000484 | C115: Michaela | D115: Kruger | E115: COD - Code | F115: SSE - Senior Software Engineer | G115: W - White | H115: F - Female | I115: SENIOR - Senior | J115: =_xlfn.XLOOKUP(B115,Sheet!A:A,Sheet!B:B,FALSE,) -> michaela@synthesis.co.za | K115: =_xlfn.XLOOKUP(B115,Sheet!A:A,Sheet!C:C,FALSE,) -> 0721619382
A116: 45299 | B116: SST000487 | C116: Kim | D116: Kramer | E116: 001 - Business Enablement Operations | F116: FOA - Front Office Administrator | G116: W - White | H116: F - Female | I116: INTERMEDIATE - Intermediate | J116: =_xlfn.XLOOKUP(B116,Sheet!A:A,Sheet!B:B,FALSE,) -> kimk@synthesis.co.za | K116: =_xlfn.XLOOKUP(B116,Sheet!A:A,Sheet!C:C,FALSE,) -> 0836012750
A117: 45323 | B117: SST000496 | C117: Njabulo | D117: Masilela | E117: CRY - Cryptography | F117: ACE - Associate Cryptography Engineer | G117: A - African | H117: M - Male | I117: INTERMEDIATE - Intermediate | J117: =_xlfn.XLOOKUP(B117,Sheet!A:A,Sheet!B:B,FALSE,) -> njabulo@synthesis.co.za | K117: =_xlfn.XLOOKUP(B117,Sheet!A:A,Sheet!C:C,FALSE,) -> 0680167887
A118: 45323 | B118: SST000498 | C118: Zander | D118: Rosslee | E118: COD - Code | F118: ISE - Intermediate Software Engineer | G118: W - White | H118: M - Male | I118: INTERMEDIATE - Intermediate | J118: =_xlfn.XLOOKUP(B118,Sheet!A:A,Sheet!B:B,FALSE,) -> Zander@synthesis.co.za | K118: =_xlfn.XLOOKUP(B118,Sheet!A:A,Sheet!C:C,FALSE,) -> 0826540532
A119: 45323 | B119: SST000502 | C119: Teveshan | D119: Valaitham | E119: REGT - RegTech | F119: PE01 - Associate Product Engineer | G119: I - Indian | H119: M - Male | I119: ASSOCIATE - Associate | J119: =_xlfn.XLOOKUP(B119,Sheet!A:A,Sheet!B:B,FALSE,) -> Teveshan@synthesis.co.za | K119: =_xlfn.XLOOKUP(B119,Sheet!A:A,Sheet!C:C,FALSE,) -> 0614834485
A120: 45323 | B120: SST000504 | C120: Liad | D120: Peretz | E120: REGT - RegTech | F120: ISE - Intermediate Software Engineer | G120: W - White | H120: M - Male | I120: INTERMEDIATE - Intermediate | J120: =_xlfn.XLOOKUP(B120,Sheet!A:A,Sheet!B:B,FALSE,) -> Liad@synthesis.co.za | K120: =_xlfn.XLOOKUP(B120,Sheet!A:A,Sheet!C:C,FALSE,) -> 0711770662
A121: 45352 | B121: SST000505 | C121: Frederick | D121: Tshimanga | E121: HAL - Halo | F121: SSE - Senior Software Engineer | G121: A - African | H121: M - Male | I121: SENIOR - Senior | J121: =_xlfn.XLOOKUP(B121,Sheet!A:A,Sheet!B:B,FALSE,) -> frederick@synthesis.co.za | K121: =_xlfn.XLOOKUP(B121,Sheet!A:A,Sheet!C:C,FALSE,) -> 0782000470
A122: 44652 | B122: SST000506 | C122: Avela | D122: Nyathela | E122: REGT - RegTech | F122: SE02 - Intermediate Support Engineer | G122: A - African | H122: M - Male | I122: INTERMEDIATE - Intermediate | J122: =_xlfn.XLOOKUP(B122,Sheet!A:A,Sheet!B:B,FALSE,) -> onke@synthesis.co.za | K122: =_xlfn.XLOOKUP(B122,Sheet!A:A,Sheet!C:C,FALSE,) -> 0723226121
A123: 44652 | B123: SST000507 | C123: Princeisac | D123: Luhanga | E123: REGT - RegTech | F123: STL - Support Team Lead | G123: A - African | H123: M - Male | I123: SENIOR - Senior | J123: =_xlfn.XLOOKUP(B123,Sheet!A:A,Sheet!B:B,FALSE,) -> prince@synthesis.co.za | K123: =_xlfn.XLOOKUP(B123,Sheet!A:A,Sheet!C:C,FALSE,) -> 0748812238
A124: 45536 | B124: SST000515 | C124: Vincent | D124: De Comarmond | E124: ID - Intelligent Data | F124: DS - Data Scientist | G124: W - White | H124: M - Male | I124: SENIOR - Senior | J124: =_xlfn.XLOOKUP(B124,Sheet!A:A,Sheet!B:B,FALSE,) -> vincentdc@synthesis.co.za | K124: =_xlfn.XLOOKUP(B124,Sheet!A:A,Sheet!C:C,FALSE,) -> 0726974424
A125: 45602 | B125: SST000516 | C125: Dirk | D125: Steynberg | E125: ID - Intelligent Data | F125: SDE - Specialist Data Engineer | G125: W - White | H125: M - Male | I125: SPECIALIST - Specialist | J125: =_xlfn.XLOOKUP(B125,Sheet!A:A,Sheet!B:B,FALSE,) -> dirk@synthesis.co.za | K125: =_xlfn.XLOOKUP(B125,Sheet!A:A,Sheet!C:C,FALSE,) -> 0609883832
... A174: 46120 | B174: SST000575 | C174: Njabulo | D174: Mashiane | E174: MAN - Managed Operations | F174: SEM - Service Manager | G174: A - African | H174: M - Male | I174: INTERMEDIATE - Intermediate | J174: =_xlfn.XLOOKUP(B174,Sheet!A:A,Sheet!B:B,FALSE,) -> njabulom@synthesis.co.za | K174: =_xlfn.XLOOKUP(B174,Sheet!A:A,Sheet!C:C,FALSE,) -> 0617419682
A175: 46113 | B175: SST000576 | C175: Brandon | D175: Fairweather | E175: COD - Code | F175: HOCS - Head of Challenger Squad | G175: W - White | H175: M - Male | I175: SENIOR - Senior
A176: 46113 | B176: SST000577 | C176: Natasha | D176: Smith | E176: COD - Code | F176: SPD - Senior Product Designer | G176: W - White | H176: F - Female | I176: SENIOR - Senior
A177: 46113 | B177: SST000578 | C177: Elizabeth | D177: Bramley | E177: TEC - Technology | F177: LDS - Lead Design Strategist | G177: W - White | H177: F - Female | I177: SENIOR - Senior
A178: 46113 | B178: SST000579 | C178: Annelize | D178: Thomas | E178: COD - Code | F178: DSL - Design Strategy Lead | G178: W - White | H178: F - Female | I178: INTERMEDIATE - Intermediate
A179: 46113 | B179: SST000580 | C179: Matthew | D179: Robinson | E179: COD - Code | F179: ED - Experience Designer | G179: W - White | H179: M - Male | I179: INTERMEDIATE - Intermediate
A180: 46140 | B180: SST000581 | C180: Randy | D180: Kubheka | E180: MAN - Managed Operations | F180: S - Support Engineer | G180: A - African | H180: M - Male | I180: JM - Junior Management | J180: =_xlfn.XLOOKUP(B180,Sheet!A:A,Sheet!B:B,FALSE,) -> randy@synthesis.co.za | K180: =_xlfn.XLOOKUP(B180,Sheet!A:A,Sheet!C:C,FALSE,) -> 0603089993
A181: 46143 | B181: SST000582 | C181: Neldan | D181: Janse Van Rensburg | E181: COD - Code | F181: T07 - Technical Lead | G181: W - White | H181: M - Male | I181: PQM - Professionally Qualified Middle Mng | J181: =_xlfn.XLOOKUP(B181,Sheet!A:A,Sheet!B:B,FALSE,) -> neldan@synthesis.co.za | K181: =_xlfn.XLOOKUP(B181,Sheet!A:A,Sheet!C:C,FALSE,) -> 0636877973
A182: 46143 | B182: SST000583 | C182: Reagan | D182: Mashiloane | E182: CLD - Cloud | F182: SCE - Senior Cloud Engineer | G182: A - African | H182: M - Male | I182: SENIOR - Senior | J182: =_xlfn.XLOOKUP(B182,Sheet!A:A,Sheet!B:B,FALSE,) -> reagan@synthesis.co.za | K182: =_xlfn.XLOOKUP(B182,Sheet!A:A,Sheet!C:C,FALSE,) -> 0789832125
A183: 44445 | B183: TB01 | C183: Tayla | D183: Boni | E183: PMO - Project Management Office | F183: HPMO - Head of PMO | G183: W - White | H183: F - Female | I183: BU_HEAD - Business Unit Head | J183: =_xlfn.XLOOKUP(B183,Sheet!A:A,Sheet!B:B,FALSE,) -> tayla@synthesis.co.za | K183: =_xlfn.XLOOKUP(B183,Sheet!A:A,Sheet!C:C,FALSE,) -> 0844322249
A184: 41106 | B184: TD01 | C184: Tjaard | D184: Du Plessis | E184: EXECUTIVE - Executive | F184: PSE - Professional Services Executive | G184: W - White | H184: M - Male | I184: SM - Senior Manager | J184: =_xlfn.XLOOKUP(B184,Sheet!A:A,Sheet!B:B,FALSE,) -> tjaard@synthesis.co.za | K184: =_xlfn.XLOOKUP(B184,Sheet!A:A,Sheet!C:C,FALSE,) -> 0827698551
A185: 43739 | B185: TH05 | C185: Tristan | D185: Hughes | E185: CLD - Cloud | F185: ISE - Intermediate Software Engineer | G185: W - White | H185: M - Male | I185: INTERMEDIATE - Intermediate | J185: =_xlfn.XLOOKUP(B185,Sheet!A:A,Sheet!B:B,FALSE,) -> tristan@synthesis.co.za | K185: =_xlfn.XLOOKUP(B185,Sheet!A:A,Sheet!C:C,FALSE,) -> 0608146381
A186: 44896 | B186: TK03 | C186: Thulani | D186: Kula | E186: MAN - Managed Operations | F186: DOE02 - Intermediate DevOps Engineer | G186: A - African | H186: M - Male | I186: INTERMEDIATE - Intermediate | J186: =_xlfn.XLOOKUP(B186,Sheet!A:A,Sheet!B:B,FALSE,) -> thulani@synthesis.co.za | K186: =_xlfn.XLOOKUP(B186,Sheet!A:A,Sheet!C:C,FALSE,) -> 0738822929
A187: 45689 | B187: TM09 | C187: Tendai | D187: Musonza | E187: CLD - Cloud | F187: CNS - Cloud Network S | G187: A - African | H187: M - Male | I187: SPECIALIST - Specialist | J187: =_xlfn.XLOOKUP(B187,Sheet!A:A,Sheet!B:B,FALSE,) -> tendaim@synthesis.co.za | K187: =_xlfn.XLOOKUP(B187,Sheet!A:A,Sheet!C:C,FALSE,) -> 0621498781
A188: 44788 | B188: TM15 | C188: Taona | D188: Madawo | E188: CLD - Cloud | F188: SA - Solutions Architect | G188: A - African | H188: M - Male | I188: SPECIALIST - Specialist | J188: =_xlfn.XLOOKUP(B188,Sheet!A:A,Sheet!B:B,FALSE,) -> taona@synthesis.co.za | K188: =_xlfn.XLOOKUP(B188,Sheet!A:A,Sheet!C:C,FALSE,) -> 0734723285
A189: 44866 | B189: TM17 | C189: Thamsanqa | D189: Mkhize | E189: REGT - RegTech | F189: IPM01 - Intermediate Cons Proj Mng | G189: A - African | H189: M - Male | I189: INTERMEDIATE - Intermediate | J189: =_xlfn.XLOOKUP(B189,Sheet!A:A,Sheet!B:B,FALSE,) -> thamsanqa@synthesis.co.za | K189: =_xlfn.XLOOKUP(B189,Sheet!A:A,Sheet!C:C,FALSE,) -> 0769027383
A190: 44896 | B190: TN01 | C190: Tamelani | D190: Netshilema | E190: REGT - RegTech | F190: SE02 - Intermediate Support Engineer | G190: A - African | H190: M - Male | I190: INTERMEDIATE - Intermediate | J190: =_xlfn.XLOOKUP(B190,Sheet!A:A,Sheet!B:B,FALSE,) -> tamelani@synthesis.co.za | K190: =_xlfn.XLOOKUP(B190,Sheet!A:A,Sheet!C:C,FALSE,) -> 0762266121
A191: 44652 | B191: WG01 | C191: William | D191: Gourley | E191: COD - Code | F191: ISE - Intermediate Software Engineer | G191: W - White | H191: M - Male | I191: INTERMEDIATE - Intermediate | J191: =_xlfn.XLOOKUP(B191,Sheet!A:A,Sheet!B:B,FALSE,) -> william@synthesis.co.za | K191: =_xlfn.XLOOKUP(B191,Sheet!A:A,Sheet!C:C,FALSE,) -> 0743849225
... A193: 44684 | B193: YR01 | C193: Yolande | D193: Roberts | E193: 003 - Sales | F193: SAM - Strategic Account Manager | G193: W - White | H193: F - Female | I193: INTERMEDIATE - Intermediate | J193: =_xlfn.XLOOKUP(B193,Sheet!A:A,Sheet!B:B,FALSE,) -> yolande@synthesis.co.za | K193: =_xlfn.XLOOKUP(B193,Sheet!A:A,Sheet!C:C,FALSE,) -> 0798113331

Sheet Sheet
A3: Employee Code | B3: Email Address | C3: Cell Number
A4: 10005 | B4: michael@synthesis.co.za | C4: 0833274929
A5: 10006 | B5: naseem@synthesis.co.za | C5: 0827493272
A6: 10009 | B6: steyn@synthesis.co.za | C6: 0834501034
A7: BS02 | B7: bhavesh@synthesis.co.za | C7: 0825423485
A8: CE01 | B8: chad@synthesis.co.za | C8: 0726304180
A9: DF01 | B9: declan@synthesis.co.za | C9: 0760458979
A10: DM03 | B10: damien@synthesis.co.za | C10: 0780592626
A11: DN01 | B11: devina@synthesis.co.za | C11: 0721058892
A12: DV04 | B12: denieke@synthesis.co.za | C12: 0726828276
A13: ER001 | B13: rodney@synthesis.co.za | C13: 0824937062
A14: GS02 | B14: garth@synthesis.co.za | C14: 0670536138
A15: JE01 | B15: james@synthesis.co.za | C15: 0662578433
A16: JJ01 | B16: jonathanj@synthesis.co.za | C16: 0741550219
A17: JL01 | B17: jonathanl@synthesis.co.za | C17: 0834501727
A18: JS01 | B18: jonathan@synthesis.co.za | C18: 0734452107
... A21: LH02 | B21: lukeh@synthesis.co.za | C21: 0728435389
A22: LM03 | C22: 0721791596
A23: LR02 | B23: leandre@synthesis.co.za | C23: 0723214345
A24: LS20 | B24: louis-philip@synthesis.co.za | C24: 0729985673
A25: MB01 | B25: marinda@synthesis.co.za | C25: 0783449276
A26: MM01 | B26: mark@synthesis.co.za | C26: 0833258246
A27: MN02 | B27: mantombi@synthesis.co.za | C27: 0739501311
A28: MS003 | C28: 0731672572
A29: MS04 | B29: martins@synthesis.co.za | C29: 0833823437
A30: MS06 | B30: muhiya@synthesis.co.za | C30: 0738742017
A31: SA01 | B31: sharon@synthesis.co.za | C31: 0714750201
A32: TB01 | B32: tayla@synthesis.co.za | C32: 0844322249
A33: TD01 | B33: tjaard@synthesis.co.za | C33: 0827698551
A34: SST000515 | B34: vincentdc@synthesis.co.za | C34: 0726974424
A35: AA01 | B35: archana@synthesis.co.za | C35: 0834186862
A36: CD01 | B36: claire@synthesis.co.za | C36: 0829658798
A37: DM01 | B37: dean@synthesis.co.za | C37: 0722575441
A38: JN01 | B38: jared@synthesis.co.za | C38: 0761151332
A39: JO001 | B39: johan@synthesis.co.za | C39: 0764233165
A40: JS02 | B40: jordan@synthesis.co.za | C40: 0712292603
... A126: SST000473 | B126: Chase@synthesis.co.za | C126: 0837002384
A127: SST000480 | C127: 0660347965
A128: SST000479 | C128: 0765181416
A129: SST000475 | B129: Paul@synthesis.co.za | C129: 0836474045
A130: SST000476 | B130: LindaniM@synthesis.co.za | C130: 0711171524
A131: SST000478 | B131: nikita@synthesis.co.za | C131: 0605204725
A132: SST000483 | B132: marcus@synthesis.co.za | C132: 0835675968
A133: SST000484 | B133: michaela@synthesis.co.za | C133: 0721619382
A134: SST000487 | B134: kimk@synthesis.co.za | C134: 0836012750
A135: SST000496 | B135: njabulo@synthesis.co.za | C135: 0680167887
A136: SST000498 | B136: Zander@synthesis.co.za | C136: 0826540532
A137: SST000502 | B137: Teveshan@synthesis.co.za | C137: 0614834485
A138: SST000504 | B138: Liad@synthesis.co.za | C138: 0711770662
A139: SST000505 | B139: frederick@synthesis.co.za | C139: 0782000470
A140: SST000516 | B140: dirk@synthesis.co.za | C140: 0609883832
... A190: SST000583 | B190: reagan@synthesis.co.za | C190: 0789832125
A191: Printed on: 2026/05/06; 18:49
